react_ipywidgets/__init__.py
react_ipywidgets/_version.py
react_ipywidgets/bqplot.py
react_ipywidgets/core.py
react_ipywidgets/find.py
react_ipywidgets/find_test.py
react_ipywidgets/generate.py
react_ipywidgets/generate_test.py
react_ipywidgets/ipycanvas.py
react_ipywidgets/ipyvue.py
react_ipywidgets/ipyvuetify.py
react_ipywidgets/ipywidgets.py
react_ipywidgets/logging.py
react_ipywidgets/py.typed
react_ipywidgets/rx.py
react_ipywidgets/test.vue
react_ipywidgets/test_core.py
react_ipywidgets/test_rx.py
react_ipywidgets/utils.py
react_ipywidgets/work.py
reacton/__init__.py
react_ipywidgets-0.11.3.dist-info/METADATA
react_ipywidgets-0.11.3.dist-info/WHEEL
react_ipywidgets-0.11.3.dist-info/licenses/LICENSE
react_ipywidgets-0.11.3.dist-info/RECORD
