Metadata-Version: 2.1
Name: react-ipywidgets
Version: 0.11.3
Project-URL: Home, https://www.github.com/widgetti/react-ipywidgets
Project-URL: Documentation, https://reacton.solara.dev
Project-URL: Source code, https://www.github.com/widgetti/react-ipywidgets
Author-email: "Maarten A. Breddels" <maartenbreddels@gmail.com>
License: The MIT License (MIT)
License-File: LICENSE
Classifier: License :: OSI Approved :: MIT License
Requires-Dist: ipywidgets
Requires-Dist: rich
Requires-Dist: typing-extensions
Provides-Extra: dev
Requires-Dist: black; extra == 'dev'
Requires-Dist: bqplot; extra == 'dev'
Requires-Dist: bump2version; extra == 'dev'
Requires-Dist: coverage; extra == 'dev'
Requires-Dist: flake8; extra == 'dev'
Requires-Dist: ipyvuetify; extra == 'dev'
Requires-Dist: jinja2; extra == 'dev'
Requires-Dist: mypy; extra == 'dev'
Requires-Dist: numpy; extra == 'dev'
Requires-Dist: pre-commit; extra == 'dev'
Requires-Dist: pytest; extra == 'dev'
Requires-Dist: pytest-cov; extra == 'dev'
